{
  "id": "54397a19-63a8-4841-a847-d2a9e93f4647",
  "prevId": "dbf2c9ef-ab92-4c3b-8f14-348198caf1e0",
  "version": "7",
  "dialect": "postgresql",
  "tables": {
    "public.bookings": {
      "name": "bookings",
      "schema": "",
      "columns": {
        "id": {
          "name": "id",
          "type": "uuid",
          "primaryKey": true,
          "notNull": true,
          "default": "gen_random_uuid()"
        },
        "user_id": {
          "name": "user_id",
          "type": "uuid",
          "primaryKey": false,
          "notNull": true
        },
        "date": {
          "name": "date",
          "type": "date",
          "primaryKey": false,
          "notNull": true
        },
        "time_slot": {
          "name": "time_slot",
          "type": "varchar(5)",
          "primaryKey": false,
          "notNull": true
        },
        "duration": {
          "name": "duration",
          "type": "integer",
          "primaryKey": false,
          "notNull": true,
          "default": 60
        },
        "created_at": {
          "name": "created_at",
          "type": "timestamp",
          "primaryKey": false,
          "notNull": true,
          "default": "now()"
        }
      },
      "indexes": {
        "idx_bookings_date": {
          "name": "idx_bookings_date",
          "columns": [
            {
              "expression": "date",
              "isExpression": false,
              "asc": true,
              "nulls": "last"
            }
          ],
          "isUnique": false,
          "concurrently": false,
          "method": "btree",
          "with": {}
        }
      },
      "foreignKeys": {
        "bookings_user_id_users_id_fk": {
          "name": "bookings_user_id_users_id_fk",
          "tableFrom": "bookings",
          "tableTo": "users",
          "columnsFrom": [
            "user_id"
          ],
          "columnsTo": [
            "id"
          ],
          "onDelete": "cascade",
          "onUpdate": "no action"
        }
      },
      "compositePrimaryKeys": {},
      "uniqueConstraints": {
        "bookings_date_time_slot_unique": {
          "name": "bookings_date_time_slot_unique",
          "nullsNotDistinct": false,
          "columns": [
            "date",
            "time_slot"
          ]
        },
        "bookings_user_id_date_unique": {
          "name": "bookings_user_id_date_unique",
          "nullsNotDistinct": false,
          "columns": [
            "user_id",
            "date"
          ]
        }
      },
      "policies": {},
      "checkConstraints": {},
      "isRLSEnabled": false
    },
    "public.users": {
      "name": "users",
      "schema": "",
      "columns": {
        "id": {
          "name": "id",
          "type": "uuid",
          "primaryKey": true,
          "notNull": true,
          "default": "gen_random_uuid()"
        },
        "name": {
          "name": "name",
          "type": "varchar(100)",
          "primaryKey": false,
          "notNull": true
        },
        "email": {
          "name": "email",
          "type": "varchar(255)",
          "primaryKey": false,
          "notNull": true
        },
        "password": {
          "name": "password",
          "type": "varchar(255)",
          "primaryKey": false,
          "notNull": true
        },
        "created_at": {
          "name": "created_at",
          "type": "timestamp",
          "primaryKey": false,
          "notNull": true,
          "default": "now()"
        }
      },
      "indexes": {},
      "foreignKeys": {},
      "compositePrimaryKeys": {},
      "uniqueConstraints": {
        "users_email_unique": {
          "name": "users_email_unique",
          "nullsNotDistinct": false,
          "columns": [
            "email"
          ]
        }
      },
      "policies": {},
      "checkConstraints": {},
      "isRLSEnabled": false
    }
  },
  "enums": {},
  "schemas": {},
  "sequences": {},
  "roles": {},
  "policies": {},
  "views": {},
  "_meta": {
    "columns": {},
    "schemas": {},
    "tables": {}
  }
}